botrun_hatch_client/__init__.py
botrun_hatch_client/client.py
botrun_hatch_client/hatch_client.py
botrun_hatch_client/storage_client.py
botrun_hatch_client/user_setting_client.py
botrun_hatch_client-5.5.211.dist-info/METADATA
botrun_hatch_client-5.5.211.dist-info/WHEEL
botrun_hatch_client-5.5.211.dist-info/RECORD
