Metadata-Version: 2.3
Name: botrun-hatch-client
Version: 5.5.211
Summary: A client library for interacting with the BotRun API
License: MIT
Author: sebastian-hsu
Author-email: sebastian.hsu@gmail.com
Requires-Python: >=3.11,<3.13
Classifier: Development Status :: 3 - Alpha
Classifier: Intended Audience :: Developers
Classifier: License :: OSI Approved :: MIT License
Classifier: Programming Language :: Python :: 3
Classifier: Programming Language :: Python :: 3.11
Classifier: Programming Language :: Python :: 3.12
Requires-Dist: aiohttp (>=3.11.13,<4.0.0)
Requires-Dist: botrun-hatch (>=5.5.201,<6.0.0)
Requires-Dist: dotenv (>=0.9.9,<0.10.0)
